{
    "ObjectType": "macpool.Pool.List",
    "Results": [
        {
            "Assigned": 13,
            "ClassId": "macpool.Pool",
            "MacBlocks": [
                {
                    "ClassId": "macpool.Block",
                    "ObjectType": "macpool.Block",
                    "Size": 256,
                    "From": "00:25:B5:BA:30:00",
                    "To": "00:25:B5:BA:30:FF"
                }
            ],
            "Moid": "677848366962753201253f74",
            "Name": "UCSX-ASB-DATA-A-MAC-POOL",
            "ObjectType": "macpool.Pool",
            "Size": 256
        },
        {
            "Assigned": 13,
            "ClassId": "macpool.Pool",
            "MacBlocks": [
                {
                    "ClassId": "macpool.Block",
                    "ObjectType": "macpool.Block",
                    "Size": 256,
                    "From": "00:25:B5:BB:30:00",
                    "To": "00:25:B5:BB:30:FF"
                }
            ],
            "Moid": "67c0839e6962753201aaf317",
            "Name": "UCSX-ASB-DATA-B-MAC-POOL",
            "ObjectType": "macpool.Pool",
            "Size": 256
        }
    ]
}